{
  "recruits": [
    {
      "name": "Josue",
      "age": "21",
      "phone": "316",
      "email": "gadir@gmail.com",
      "address": "cra34a",
      "birthdate": "13/04/2002",
      "identification_number": "1095844",
      "admission_date": "21/12/2022",
      "teamId": "1",
      "id": 1683890647389
    },
    {
      "name": "pedro",
      "age": "23",
      "phone": "234234",
      "email": "pedro@gmail.com",
      "address": "calle20",
      "birthdate": "2023-05-04",
      "identification_number": "21312321",
      "admission_date": "2023-01-04",
      "teamId": "2",
      "id": 1684159219189
    },
    {
      "name": "maria",
      "age": "33",
      "phone": "3453453",
      "email": "maria@gmail.com",
      "address": "cra44",
      "birthdate": "2015-06-09",
      "identification_number": "123234",
      "admission_date": "2023-04-19",
      "teamId": "3",
      "id": 1684159302883
    },
    {
      "name": "juan",
      "age": "18",
      "phone": "2131",
      "email": "juan@gmail",
      "address": "cra98",
      "birthdate": "2023-05-12",
      "identification_number": "12321",
      "admission_date": "2022-12-09",
      "teamId": "2",
      "id": 1684159884005
    },
    {
      "name": "fgn",
      "age": "17",
      "phone": "045054",
      "email": "hdfhfd",
      "address": "hdfhfd",
      "birthdate": "2023-05-04",
      "identification_number": "12",
      "admission_date": "2023-05-18",
      "teamId": "4",
      "id": 1684159932169
    },
    {
      "name": "cila",
      "age": "16",
      "phone": "2134213",
      "email": "cila@gmail.com",
      "address": "cra32",
      "identification_number": "1232133",
      "teamId": "1",
      "birthdate": "2023-05-04",
      "admission_date": "2023-02-15",
      "id": 1684178947272
    }
  ],
  "team": [
    {
      "id": 1,
      "name": "spuhtnik",
      "trainer_asociado": "Miguel"
    }
  ],
  "skill": [
    {
      "id": 3,
      "name": ""
    }
  ],
  "modulo_skill": [
    {
      "id": 4,
      "name": "",
      "id_skill": ""
    }
  ],
  "assessment": [
    {
      "id_recluta": 5,
      "id_modulo": "",
      "nota": ""
    }
  ]
}